vacasa_opentelemetry/__init__.py
vacasa_opentelemetry/otel.py
vacasa_opentelemetry-1.0.0.dist-info/METADATA
vacasa_opentelemetry-1.0.0.dist-info/WHEEL
vacasa_opentelemetry-1.0.0.dist-info/RECORD
