Metadata-Version: 2.4
Name: vacasa-opentelemetry
Version: 1.0.0
Summary: OpenTelemetry helpers for Vacasa Python services
License: MIT
Author: Vacasa
Author-email: engineering@vacasa.com
Requires-Python: >=3.8.1,<4.0.0
Classifier: License :: OSI Approved :: MIT License
Classifier: Programming Language :: Python :: 3
Classifier: Programming Language :: Python :: 3.9
Classifier: Programming Language :: Python :: 3.10
Classifier: Programming Language :: Python :: 3.11
Classifier: Programming Language :: Python :: 3.12
Classifier: Programming Language :: Python :: 3.13
Classifier: Programming Language :: Python :: 3.14
Requires-Dist: opentelemetry-api (>=1.20.0,<2.0.0)
Requires-Dist: opentelemetry-exporter-otlp-proto-http (>=1.20.0,<2.0.0)
Requires-Dist: opentelemetry-instrumentation-logging (>=0.41b0,<0.42)
Requires-Dist: opentelemetry-sdk (>=1.20.0,<2.0.0)
Requires-Dist: opentelemetry-semantic-conventions (>=0.41b0,<0.42)
Project-URL: Homepage, https://github.com/Vacasa/node-util-ts-lib
Project-URL: Repository, https://github.com/Vacasa/node-util-ts-lib
